{"format":2,"version":"5.5","globals":"ca8ba9bd7f80b7dd7a627c9e9790c38f","files":{"movies_admin_py":{"hash":"23b3f8ab894286afb6416200cf284c31","index":{"nums":[1,1,0,0,0,0,0],"html_filename":"movies_admin_py.html","relative_filename":"movies/admin.py"}},"movies_apps_py":{"hash":"d17966b965994eeadb1ccc62de476039","index":{"nums":[1,3,0,0,0,0,0],"html_filename":"movies_apps_py.html","relative_filename":"movies/apps.py"}},"movies_forms_py":{"hash":"fb88bb8801a3a3eeaca053bd204b98db","index":{"nums":[1,3,0,0,0,0,0],"html_filename":"movies_forms_py.html","relative_filename":"movies/forms.py"}},"movies_imdb_api_py":{"hash":"2e945b35f8fe73fd6f8aa99a8afeea4b","index":{"nums":[1,14,0,0,0,0,0],"html_filename":"movies_imdb_api_py.html","relative_filename":"movies/imdb_api.py"}},"movies_imdbpy_api_py":{"hash":"15cf5e275962af38783086306f4cf4fb","index":{"nums":[1,12,0,12,0,0,0],"html_filename":"movies_imdbpy_api_py.html","relative_filename":"movies/imdbpy_api.py"}},"movies_import_api_py":{"hash":"7ee1ae397cfc9846682b887d53a58548","index":{"nums":[1,50,0,50,0,0,0],"html_filename":"movies_import_api_py.html","relative_filename":"movies/import_api.py"}},"movies_managers_py":{"hash":"fbbd23bea0e51f0dcc0a4a5cf67a22d7","index":{"nums":[1,22,0,0,0,0,0],"html_filename":"movies_managers_py.html","relative_filename":"movies/managers.py"}},"movies_migrations_0001_initial_py":{"hash":"051c1200e8fbb59ec4bbb8933e93b078","index":{"nums":[1,5,0,0,0,0,0],"html_filename":"movies_migrations_0001_initial_py.html","relative_filename":"movies/migrations/0001_initial.py"}},"movies_migrations_0002_auto_20210326_0854_py":{"hash":"003a41b72d88700d70314a2d3ce9c3ec","index":{"nums":[1,4,0,0,0,0,0],"html_filename":"movies_migrations_0002_auto_20210326_0854_py.html","relative_filename":"movies/migrations/0002_auto_20210326_0854.py"}},"movies_models_py":{"hash":"4173907c66cb5aee2942cc863955acfd","index":{"nums":[1,24,0,0,0,0,0],"html_filename":"movies_models_py.html","relative_filename":"movies/models.py"}},"movies_urls_py":{"hash":"027e4da6cbf10b28be6656be74ebb451","index":{"nums":[1,3,0,0,0,0,0],"html_filename":"movies_urls_py.html","relative_filename":"movies/urls.py"}},"movies_views_py":{"hash":"3c7380aa9aa9c7d371398193b879accc","index":{"nums":[1,52,0,5,0,0,0],"html_filename":"movies_views_py.html","relative_filename":"movies/views.py"}},"users_admin_py":{"hash":"be77ee8ba3bc033fbe590be51bed32fb","index":{"nums":[1,4,0,0,0,0,0],"html_filename":"users_admin_py.html","relative_filename":"users/admin.py"}},"users_apps_py":{"hash":"d9d986f51eda4426b37018de602670f2","index":{"nums":[1,3,0,0,0,0,0],"html_filename":"users_apps_py.html","relative_filename":"users/apps.py"}},"users_forms_py":{"hash":"fd75f778dae2d25acfdaf821f770e4a0","index":{"nums":[1,20,0,1,0,0,0],"html_filename":"users_forms_py.html","relative_filename":"users/forms.py"}},"users_migrations_0001_initial_py":{"hash":"97303342f0da71978371bb9834c1b8ab","index":{"nums":[1,8,0,0,0,0,0],"html_filename":"users_migrations_0001_initial_py.html","relative_filename":"users/migrations/0001_initial.py"}},"users_models_py":{"hash":"55eba987b082c481576c7c4dfffb812f","index":{"nums":[1,5,0,0,0,0,0],"html_filename":"users_models_py.html","relative_filename":"users/models.py"}},"users_urls_py":{"hash":"a26b2b8b23791d4e2048a0cbf3b98c8c","index":{"nums":[1,4,0,0,0,0,0],"html_filename":"users_urls_py.html","relative_filename":"users/urls.py"}},"users_views_py":{"hash":"b5b8ddf88975ada682c0d776fa8499d3","index":{"nums":[1,51,0,4,0,0,0],"html_filename":"users_views_py.html","relative_filename":"users/views.py"}}}}